README.rst
setup.py
django_gp_auth.egg-info/PKG-INFO
django_gp_auth.egg-info/SOURCES.txt
django_gp_auth.egg-info/dependency_links.txt
django_gp_auth.egg-info/top_level.txt
gpauth/__init__.py
gpauth/admin.py
gpauth/apps.py
gpauth/models.py
gpauth/migrations/0001_initial.py
gpauth/migrations/__init__.py