Metadata-Version: 1.1
Name: django-gp-auth
Version: 1.0.0.dev1
Summary: GP Auth is a simple application Django to manage the registration of users in a customized manner system
Home-page: https://github.com/gilsonbp/gp-auth
Author: Gilson Paulino
Author-email: gilsonbp@gmail.com
License: MIT
Keywords: Gilson Paulino GP Developer
Platform: UNKNOWN
Classifier: Development Status :: 4 - Beta
Classifier: Framework :: Django
Classifier: Framework :: Django :: 1.9
Classifier: Intended Audience :: Developers
Classifier: Topic :: Software Development
Classifier: License :: OSI Approved :: MIT License
Classifier: Operating System :: OS Independent
Classifier: Programming Language :: Python
Classifier: Programming Language :: Python :: 3
Classifier: Programming Language :: Python :: 3.4
Classifier: Programming Language :: Python :: 3.5
